slidercode/__init__.py
slidercode/test_py.py
slidercode-0.4.dist-info/DESCRIPTION.rst
slidercode-0.4.dist-info/METADATA
slidercode-0.4.dist-info/RECORD
slidercode-0.4.dist-info/WHEEL
slidercode-0.4.dist-info/metadata.json
slidercode-0.4.dist-info/top_level.txt
