Metadata-Version: 2.0
Name: slidercode
Version: 0.4
Summary: SDK about slider code
Home-page: https://pypi.org/project/slidercode/
Author: Barneyness
Author-email: 1163060039@qq.com
License: UNKNOWN
Platform: UNKNOWN
Classifier: Programming Language :: Python :: 3
Classifier: License :: OSI Approved :: MIT License
Classifier: Operating System :: OS Independent
Requires-Dist: requests
Requires-Dist: matplotlib
Requires-Dist: numpy
